python_hll/__init__.py
python_hll/hll.py
python_hll/hlltype.py
python_hll/hllutil.py
python_hll/serialization.py
python_hll/util.py
python_hll-0.1.3.dist-info/DESCRIPTION.rst
python_hll-0.1.3.dist-info/METADATA
python_hll-0.1.3.dist-info/RECORD
python_hll-0.1.3.dist-info/WHEEL
python_hll-0.1.3.dist-info/metadata.json
python_hll-0.1.3.dist-info/top_level.txt
