Metadata-Version: 2.0
Name: python-hll
Version: 0.1.3
Summary: Python library for the HyperLogLog algorithm
Home-page: https://github.com/AdRoll/python-hll
Author: Jon Aquino
Author-email: jonathan.aquino@adroll.com
License: MIT license
Keywords: python_hll
Platform: UNKNOWN
Classifier: Development Status :: 2 - Pre-Alpha
Classifier: Intended Audience :: Developers
Classifier: License :: OSI Approved :: MIT License
Classifier: Natural Language :: English
Classifier: Programming Language :: Python :: 2
Classifier: Programming Language :: Python :: 2.7
Classifier: Programming Language :: Python :: 3
Classifier: Programming Language :: Python :: 3.4
Classifier: Programming Language :: Python :: 3.5
Classifier: Programming Language :: Python :: 3.6
Classifier: Programming Language :: Python :: 3.7
Requires-Dist: numpy
